pyrediscore/__init__.py
pyrediscore/redantic.py
pyrediscore/utils.py
pyrediscore-1.0.3.dist-info/METADATA
pyrediscore-1.0.3.dist-info/WHEEL
pyrediscore-1.0.3.dist-info/licenses/LICENSE
pyrediscore-1.0.3.dist-info/RECORD
