Metadata-Version: 2.4
Name: pyrediscore
Version: 1.0.3
Summary: Low-level decorators for redis instance I/O operations
License-File: LICENSE
Requires-Python: >=3.7
Requires-Dist: decorator>=5.0.9
Requires-Dist: marshmallow<4.0
Requires-Dist: pydantic>=1.9
Requires-Dist: redis>=4.2
